mypandas/Probabilities_and_Statistics.py
mypandas/pandas_read_file.py
mypandas2024_JKK-0.0.3.dist-info/LICENSE
mypandas2024_JKK-0.0.3.dist-info/METADATA
mypandas2024_JKK-0.0.3.dist-info/WHEEL
mypandas2024_JKK-0.0.3.dist-info/top_level.txt
mypandas2024_JKK-0.0.3.dist-info/RECORD
