Metadata-Version: 2.1
Name: mypandas2024-JKK
Version: 0.0.3
Summary: oss-dev mypandas app 0003
Home-page: 
Author: Jaekyeong_Kim
Classifier: Programming Language :: Python :: 3
Classifier: Operating System :: OS Independent
License-File: LICENSE
Requires-Dist: pandas
Requires-Dist: numpy
Requires-Dist: matplotlib
Requires-Dist: scipy
